{"cameraMode":{"drawMode":0,"name":"Shaded","section":"Shading Mode"},"sceneLighting":true,"audioPlay":false,"sceneViewState":{"m_AlwaysRefresh":false,"showFog":true,"showSkybox":true,"showFlares":true,"showImageEffects":true,"showParticleSystems":true,"showVisualEffectGraphs":true,"m_FxEnabled":true},"in2DMode":false,"pivot":{"x":67.39266967773438,"y":-60.465309143066409,"z":14.99241828918457},"rotation":{"x":-0.29890966415405276,"y":-0.559583306312561,"z":0.2263026088476181,"w":-0.7391067147254944},"size":60.09355163574219,"orthographic":false}